data/__init__.py
data/data_dict.py
data/utilities.py
mlautomator/__init__.py
mlautomator/get_model.py
mlautomator/mlautomator.py
mlautomator/search_keys.py
mlautomator/search_spaces.py
mlautomator/objectives/__init__.py
mlautomator/objectives/classifier_objectives.py
mlautomator/objectives/regressor_objectives.py
test/__init__.py
test/test_classifiers.py
test/test_mlautomator.py
test/test_regressors.py
mlautomator-1.0.3.dist-info/LICENSE
mlautomator-1.0.3.dist-info/METADATA
mlautomator-1.0.3.dist-info/WHEEL
mlautomator-1.0.3.dist-info/top_level.txt
mlautomator-1.0.3.dist-info/RECORD
