Metadata-Version: 2.1
Name: mlautomator
Version: 1.0.3
Summary: A fast, simple way to train machine learning algorithms
Home-page: https://github.com/VanAurum/ML-automator
Author: Kevin Vecmanis
Author-email: kevinvecmanis@gmail.com
License: UNKNOWN
Platform: UNKNOWN
Classifier: Programming Language :: Python :: 3
Classifier: License :: OSI Approved :: MIT License
Classifier: Operating System :: OS Independent
Requires-Dist: numpy
Requires-Dist: pandas
Requires-Dist: sklearn
Requires-Dist: hyperopt
Requires-Dist: xgboost
